MANIFEST.in
README.md
setup.py
autograph/__init__.py
autograph/admin.py
autograph/models.py
autograph/tests.py
autograph/utils.py
autograph.egg-info/PKG-INFO
autograph.egg-info/SOURCES.txt
autograph.egg-info/dependency_links.txt
autograph.egg-info/requires.txt
autograph.egg-info/top_level.txt
autograph/migrations/0001_initial.py
autograph/migrations/__init__.py